libs_gds/__init__.py
libs_gds/gds_tiktok.py
libs_appium-0.0.1.dist-info/LICENSE
libs_appium-0.0.1.dist-info/METADATA
libs_appium-0.0.1.dist-info/WHEEL
libs_appium-0.0.1.dist-info/top_level.txt
libs_appium-0.0.1.dist-info/RECORD
